models/Densenet.py
models/HRNet.py
models/Inception-ResNet-V2.py
models/InceptionResNetV2.py
models/VoVNet.py
models/__init__.py
models/shuffelnet (2).py
models/shuffelnet.py
models/vgg19(1).py
models/vgg19.py
transfer_learning_tensor-0.2.dist-info/LICENCE.txt
transfer_learning_tensor-0.2.dist-info/METADATA
transfer_learning_tensor-0.2.dist-info/WHEEL
transfer_learning_tensor-0.2.dist-info/top_level.txt
transfer_learning_tensor-0.2.dist-info/RECORD
