Metadata-Version: 2.1
Name: transfer-learning-tensor
Version: 0.2
Summary: This Models tensorflow Transferlearning
Home-page: UNKNOWN
Author: Ahmed Elmasry
Author-email: ahmedalnasr22@gmail.com
License: UNKNOWN
Platform: UNKNOWN
Classifier: Programming Language :: Python :: 3
Classifier: License :: OSI Approved :: MIT License
Classifier: Operating System :: OS Independent
